[{"station":948700,"date":"31\/12\/2016","air_temperature_celcius":19,"relative_humidity":56.8,"windspeed_knots":7.9,"max_wind_speed":11.1,"precipitation ":" 0.00I"},{"station":948700,"date":"2\/01\/2017","air_temperature_celcius":15,"relative_humidity":50.7,"windspeed_knots":9.2,"max_wind_speed":13.0,"precipitation ":" 0.02G"},{"station":948700,"date":"3\/01\/2017","air_temperature_celcius":16,"relative_humidity":53.6,"windspeed_knots":8.1,"max_wind_speed":15.0,"precipitation ":" 0.00G"},{"station":948700,"date":"4\/01\/2017","air_temperature_celcius":24,"relative_humidity":61.6,"windspeed_knots":7.7,"max_wind_speed":14.0,"precipitation ":" 0.00I"},{"station":948700,"date":"5\/01\/2017","air_temperature_celcius":24,"relative_humidity":62.3,"windspeed_knots":7.0,"max_wind_speed":13.0,"precipitation ":" 0.00I"},{"station":948700,"date":"6\/01\/2017","air_temperature_celcius":26,"relative_humidity":60.8,"windspeed_knots":6.9,"max_wind_speed":12.0,"precipitation ":" 0.00I"},{"station":948700,"date":"7\/01\/2017","air_temperature_celcius":32,"relative_humidity":54.1,"windspeed_knots":12.8,"max_wind_speed":19.0,"precipitation ":" 0.00I"},{"station":948700,"date":"8\/01\/2017","air_temperature_celcius":20,"relative_humidity":57.7,"windspeed_knots":9.9,"max_wind_speed":18.1,"precipitation ":" 0.00I"},{"station":948700,"date":"9\/01\/2017","air_temperature_celcius":19,"relative_humidity":56.3,"windspeed_knots":5.8,"max_wind_speed":8.9,"precipitation ":" 0.00I"},{"station":948700,"date":"10\/01\/2017","air_temperature_celcius":20,"relative_humidity":57.0,"windspeed_knots":8.7,"max_wind_speed":13.0,"precipitation ":" 0.00I"},{"station":948700,"date":"11\/01\/2017","air_temperature_celcius":18,"relative_humidity":53.3,"windspeed_knots":7.9,"max_wind_speed":14.0,"precipitation ":" 0.00I"},{"station":948700,"date":"12\/01\/2017","air_temperature_celcius":22,"relative_humidity":56.3,"windspeed_knots":8.0,"max_wind_speed":13.0,"precipitation ":" 0.08G"},{"station":948700,"date":"13\/01\/2017","air_temperature_celcius":19,"relative_humidity":54.1,"windspeed_knots":11.2,"max_wind_speed":18.1,"precipitation ":" 0.31G"},{"station":948700,"date":"14\/01\/2017","air_temperature_celcius":17,"relative_humidity":50.4,"windspeed_knots":11.9,"max_wind_speed":16.9,"precipitation ":" 0.00G"},{"station":948700,"date":"15\/01\/2017","air_temperature_celcius":16,"relative_humidity":50.8,"windspeed_knots":5.8,"max_wind_speed":12.0,"precipitation ":" 0.00I"},{"station":948700,"date":"16\/01\/2017","air_temperature_celcius":24,"relative_humidity":55.4,"windspeed_knots":5.9,"max_wind_speed":9.9,"precipitation ":" 0.00I"},{"station":948700,"date":"17\/01\/2017","air_temperature_celcius":24,"relative_humidity":53.4,"windspeed_knots":9.9,"max_wind_speed":15.9,"precipitation ":" 0.00I"},{"station":948700,"date":"18\/01\/2017","air_temperature_celcius":16,"relative_humidity":46.7,"windspeed_knots":10.0,"max_wind_speed":16.9,"precipitation ":" 0.00I"},{"station":948700,"date":"19\/01\/2017","air_temperature_celcius":19,"relative_humidity":57.2,"windspeed_knots":8.9,"max_wind_speed":15.0,"precipitation ":" 0.98G"},{"station":948700,"date":"20\/01\/2017","air_temperature_celcius":16,"relative_humidity":50.9,"windspeed_knots":12.9,"max_wind_speed":21.0,"precipitation ":" 0.03G"},{"station":948700,"date":"21\/01\/2017","air_temperature_celcius":17,"relative_humidity":52.5,"windspeed_knots":6.7,"max_wind_speed":12.0,"precipitation ":" 0.00G"},{"station":948700,"date":"22\/01\/2017","air_temperature_celcius":23,"relative_humidity":59.0,"windspeed_knots":6.0,"max_wind_speed":12.0,"precipitation ":" 0.00I"},{"station":948700,"date":"23\/01\/2017","air_temperature_celcius":25,"relative_humidity":58.3,"windspeed_knots":12.2,"max_wind_speed":22.0,"precipitation ":" 0.04G"},{"station":948700,"date":"24\/01\/2017","air_temperature_celcius":16,"relative_humidity":48.2,"windspeed_knots":9.9,"max_wind_speed":18.1,"precipitation ":" 0.01G"},{"station":948700,"date":"25\/01\/2017","air_temperature_celcius":17,"relative_humidity":50.8,"windspeed_knots":9.0,"max_wind_speed":15.9,"precipitation ":" 0.00G"},{"station":948700,"date":"26\/01\/2017","air_temperature_celcius":18,"relative_humidity":53.5,"windspeed_knots":8.8,"max_wind_speed":13.0,"precipitation ":" 0.00I"},{"station":948700,"date":"27\/01\/2017","air_temperature_celcius":19,"relative_humidity":56.1,"windspeed_knots":6.9,"max_wind_speed":12.0,"precipitation ":" 0.00A"},{"station":948700,"date":"28\/01\/2017","air_temperature_celcius":18,"relative_humidity":57.0,"windspeed_knots":7.4,"max_wind_speed":15.0,"precipitation ":" 0.00I"},{"station":948700,"date":"29\/01\/2017","air_temperature_celcius":22,"relative_humidity":58.0,"windspeed_knots":6.9,"max_wind_speed":12.0,"precipitation ":" 0.00I"},{"station":948700,"date":"30\/01\/2017","air_temperature_celcius":20,"relative_humidity":55.8,"windspeed_knots":10.5,"max_wind_speed":15.9,"precipitation ":" 0.01G"},{"station":948700,"date":"31\/01\/2017","air_temperature_celcius":16,"relative_humidity":48.4,"windspeed_knots":8.1,"max_wind_speed":15.9,"precipitation ":" 0.00G"},{"station":948700,"date":"1\/02\/2017","air_temperature_celcius":16,"relative_humidity":48.9,"windspeed_knots":5.4,"max_wind_speed":8.9,"precipitation ":" 0.00I"},{"station":948700,"date":"2\/02\/2017","air_temperature_celcius":18,"relative_humidity":53.0,"windspeed_knots":6.6,"max_wind_speed":14.0,"precipitation ":" 0.00I"},{"station":948700,"date":"3\/02\/2017","air_temperature_celcius":18,"relative_humidity":54.4,"windspeed_knots":5.7,"max_wind_speed":9.9,"precipitation ":" 0.00I"},{"station":948700,"date":"4\/02\/2017","air_temperature_celcius":26,"relative_humidity":53.7,"windspeed_knots":8.7,"max_wind_speed":15.0,"precipitation ":" 0.00I"},{"station":948700,"date":"5\/02\/2017","air_temperature_celcius":21,"relative_humidity":64.5,"windspeed_knots":10.6,"max_wind_speed":15.9,"precipitation ":" 1.26G"},{"station":948700,"date":"6\/02\/2017","air_temperature_celcius":16,"relative_humidity":48.1,"windspeed_knots":9.3,"max_wind_speed":12.0,"precipitation ":" 0.00G"},{"station":948700,"date":"7\/02\/2017","air_temperature_celcius":20,"relative_humidity":57.4,"windspeed_knots":10.9,"max_wind_speed":22.0,"precipitation ":" 0.00I"},{"station":948700,"date":"8\/02\/2017","air_temperature_celcius":31,"relative_humidity":61.9,"windspeed_knots":14.1,"max_wind_speed":23.9,"precipitation ":" 0.00I"},{"station":948700,"date":"9\/02\/2017","air_temperature_celcius":22,"relative_humidity":62.7,"windspeed_knots":7.6,"max_wind_speed":18.1,"precipitation ":" 0.00I"},{"station":948700,"date":"10\/02\/2017","air_temperature_celcius":21,"relative_humidity":60.4,"windspeed_knots":6.8,"max_wind_speed":12.0,"precipitation ":" 0.00I"},{"station":948700,"date":"11\/02\/2017","air_temperature_celcius":19,"relative_humidity":53.8,"windspeed_knots":9.2,"max_wind_speed":15.0,"precipitation ":" 0.02G"},{"station":948700,"date":"12\/02\/2017","air_temperature_celcius":16,"relative_humidity":48.3,"windspeed_knots":14.4,"max_wind_speed":19.0,"precipitation ":" 0.00G"},{"station":948700,"date":"13\/02\/2017","air_temperature_celcius":16,"relative_humidity":53.6,"windspeed_knots":12.1,"max_wind_speed":16.9,"precipitation ":" 0.16G"},{"station":948700,"date":"14\/02\/2017","air_temperature_celcius":14,"relative_humidity":48.5,"windspeed_knots":7.3,"max_wind_speed":14.0,"precipitation ":" 0.00G"},{"station":948700,"date":"15\/02\/2017","air_temperature_celcius":22,"relative_humidity":53.4,"windspeed_knots":10.9,"max_wind_speed":19.0,"precipitation ":" 0.00I"},{"station":948700,"date":"16\/02\/2017","air_temperature_celcius":18,"relative_humidity":53.6,"windspeed_knots":7.2,"max_wind_speed":15.0,"precipitation ":" 0.00I"},{"station":948700,"date":"17\/02\/2017","air_temperature_celcius":18,"relative_humidity":49.4,"windspeed_knots":9.3,"max_wind_speed":13.0,"precipitation ":" 0.00I"},{"station":948700,"date":"18\/02\/2017","air_temperature_celcius":15,"relative_humidity":44.6,"windspeed_knots":9.7,"max_wind_speed":12.0,"precipitation ":" 0.02G"},{"station":948700,"date":"19\/02\/2017","air_temperature_celcius":13,"relative_humidity":48.5,"windspeed_knots":10.7,"max_wind_speed":14.0,"precipitation ":" 0.71G"},{"station":948701,"date":"20\/02\/2017","air_temperature_celcius":15,"relative_humidity":49.1,"windspeed_knots":9.6,"max_wind_speed":16.9,"precipitation ":" 0.01G"},{"station":948701,"date":"21\/02\/2017","air_temperature_celcius":16,"relative_humidity":51.0,"windspeed_knots":6.0,"max_wind_speed":13.0,"precipitation ":" 0.00G"},{"station":948701,"date":"22\/02\/2017","air_temperature_celcius":23,"relative_humidity":49.6,"windspeed_knots":10.0,"max_wind_speed":19.0,"precipitation ":" 0.00I"},{"station":948701,"date":"23\/02\/2017","air_temperature_celcius":18,"relative_humidity":55.5,"windspeed_knots":8.9,"max_wind_speed":15.0,"precipitation ":" 0.01G"},{"station":948701,"date":"24\/02\/2017","air_temperature_celcius":16,"relative_humidity":48.3,"windspeed_knots":9.4,"max_wind_speed":14.0,"precipitation ":" 0.01G"},{"station":948701,"date":"25\/02\/2017","air_temperature_celcius":17,"relative_humidity":52.6,"windspeed_knots":10.3,"max_wind_speed":15.9,"precipitation ":" 0.00G"},{"station":948701,"date":"26\/02\/2017","air_temperature_celcius":21,"relative_humidity":54.9,"windspeed_knots":7.4,"max_wind_speed":16.9,"precipitation ":" 0.00I"},{"station":948701,"date":"27\/02\/2017","air_temperature_celcius":24,"relative_humidity":55.6,"windspeed_knots":5.9,"max_wind_speed":13.0,"precipitation ":" 0.00I"},{"station":948701,"date":"28\/02\/2017","air_temperature_celcius":23,"relative_humidity":54.1,"windspeed_knots":5.7,"max_wind_speed":14.0,"precipitation ":" 0.00I"},{"station":948701,"date":"1\/03\/2017","air_temperature_celcius":21,"relative_humidity":57.3,"windspeed_knots":5.4,"max_wind_speed":9.9,"precipitation ":" 0.00I"},{"station":948701,"date":"2\/03\/2017","air_temperature_celcius":20,"relative_humidity":62.6,"windspeed_knots":10.1,"max_wind_speed":15.0,"precipitation ":" 0.00I"},{"station":948701,"date":"3\/03\/2017","air_temperature_celcius":21,"relative_humidity":59.5,"windspeed_knots":12.4,"max_wind_speed":21.0,"precipitation ":" 0.00I"},{"station":948701,"date":"4\/03\/2017","air_temperature_celcius":22,"relative_humidity":62.0,"windspeed_knots":7.9,"max_wind_speed":11.1,"precipitation ":" 0.00I"},{"station":948701,"date":"5\/03\/2017","air_temperature_celcius":20,"relative_humidity":58.8,"windspeed_knots":11.5,"max_wind_speed":15.9,"precipitation ":" 0.00I"},{"station":948701,"date":"6\/03\/2017","air_temperature_celcius":20,"relative_humidity":52.9,"windspeed_knots":17.0,"max_wind_speed":21.0,"precipitation ":" 0.00I"},{"station":948701,"date":"7\/03\/2017","air_temperature_celcius":19,"relative_humidity":51.5,"windspeed_knots":10.2,"max_wind_speed":20.0,"precipitation ":" 0.00I"},{"station":948701,"date":"8\/03\/2017","air_temperature_celcius":21,"relative_humidity":51.7,"windspeed_knots":7.2,"max_wind_speed":13.0,"precipitation ":" 0.00I"},{"station":948701,"date":"9\/03\/2017","air_temperature_celcius":23,"relative_humidity":53.4,"windspeed_knots":6.1,"max_wind_speed":11.1,"precipitation ":" 0.00I"},{"station":948701,"date":"10\/03\/2017","air_temperature_celcius":19,"relative_humidity":60.2,"windspeed_knots":6.4,"max_wind_speed":12.0,"precipitation ":" 0.00I"},{"station":948701,"date":"11\/03\/2017","air_temperature_celcius":20,"relative_humidity":59.7,"windspeed_knots":8.6,"max_wind_speed":15.9,"precipitation ":" 0.01G"},{"station":948701,"date":"12\/03\/2017","air_temperature_celcius":21,"relative_humidity":58.1,"windspeed_knots":5.3,"max_wind_speed":11.1,"precipitation ":" 0.00G"},{"station":948701,"date":"13\/03\/2017","air_temperature_celcius":20,"relative_humidity":62.2,"windspeed_knots":7.1,"max_wind_speed":15.0,"precipitation ":" 0.00I"},{"station":948701,"date":"14\/03\/2017","air_temperature_celcius":25,"relative_humidity":58.3,"windspeed_knots":7.1,"max_wind_speed":13.0,"precipitation ":" 0.00I"},{"station":948701,"date":"15\/03\/2017","air_temperature_celcius":28,"relative_humidity":58.4,"windspeed_knots":11.9,"max_wind_speed":18.1,"precipitation ":" 0.04G"},{"station":948701,"date":"16\/03\/2017","air_temperature_celcius":18,"relative_humidity":53.3,"windspeed_knots":10.8,"max_wind_speed":15.0,"precipitation ":" 0.00G"},{"station":948701,"date":"17\/03\/2017","air_temperature_celcius":18,"relative_humidity":51.1,"windspeed_knots":8.1,"max_wind_speed":15.0,"precipitation ":" 0.00I"},{"station":948701,"date":"18\/03\/2017","air_temperature_celcius":21,"relative_humidity":52.8,"windspeed_knots":4.1,"max_wind_speed":11.1,"precipitation ":" 0.00I"},{"station":948701,"date":"19\/03\/2017","air_temperature_celcius":24,"relative_humidity":55.2,"windspeed_knots":5.8,"max_wind_speed":11.1,"precipitation ":" 0.00I"},{"station":948701,"date":"20\/03\/2017","air_temperature_celcius":23,"relative_humidity":63.8,"windspeed_knots":7.1,"max_wind_speed":15.9,"precipitation ":" 0.08G"},{"station":948701,"date":"21\/03\/2017","air_temperature_celcius":20,"relative_humidity":67.4,"windspeed_knots":8.5,"max_wind_speed":14.0,"precipitation ":" 0.63G"},{"station":948701,"date":"22\/03\/2017","air_temperature_celcius":18,"relative_humidity":57.5,"windspeed_knots":16.1,"max_wind_speed":21.0,"precipitation ":" 0.00G"},{"station":948701,"date":"23\/03\/2017","air_temperature_celcius":18,"relative_humidity":55.6,"windspeed_knots":12.8,"max_wind_speed":19.0,"precipitation ":" 0.00I"},{"station":948701,"date":"24\/03\/2017","air_temperature_celcius":20,"relative_humidity":58.4,"windspeed_knots":6.1,"max_wind_speed":11.1,"precipitation ":" 0.00I"},{"station":948701,"date":"25\/03\/2017","air_temperature_celcius":23,"relative_humidity":61.9,"windspeed_knots":8.0,"max_wind_speed":15.9,"precipitation ":" 0.00I"},{"station":948701,"date":"26\/03\/2017","air_temperature_celcius":23,"relative_humidity":60.6,"windspeed_knots":10.1,"max_wind_speed":26.0,"precipitation ":" 0.00I"},{"station":948701,"date":"27\/03\/2017","air_temperature_celcius":17,"relative_humidity":53.4,"windspeed_knots":9.4,"max_wind_speed":25.1,"precipitation ":" 0.16G"},{"station":948701,"date":"28\/03\/2017","air_temperature_celcius":18,"relative_humidity":50.6,"windspeed_knots":6.0,"max_wind_speed":13.0,"precipitation ":" 0.00G"},{"station":948701,"date":"29\/03\/2017","air_temperature_celcius":17,"relative_humidity":49.9,"windspeed_knots":12.2,"max_wind_speed":21.0,"precipitation ":" 0.24G"},{"station":948701,"date":"30\/03\/2017","air_temperature_celcius":13,"relative_humidity":47.0,"windspeed_knots":7.9,"max_wind_speed":15.0,"precipitation ":" 0.02G"},{"station":948701,"date":"31\/03\/2017","air_temperature_celcius":14,"relative_humidity":45.8,"windspeed_knots":6.5,"max_wind_speed":9.9,"precipitation ":" 0.00G"},{"station":948701,"date":"1\/04\/2017","air_temperature_celcius":14,"relative_humidity":45.7,"windspeed_knots":9.2,"max_wind_speed":15.9,"precipitation ":" 0.00I"},{"station":948701,"date":"2\/04\/2017","air_temperature_celcius":12,"relative_humidity":43.4,"windspeed_knots":9.3,"max_wind_speed":15.0,"precipitation ":" 0.00I"},{"station":948701,"date":"3\/04\/2017","air_temperature_celcius":15,"relative_humidity":47.7,"windspeed_knots":5.9,"max_wind_speed":13.0,"precipitation ":" 0.00I"},{"station":948701,"date":"4\/04\/2017","air_temperature_celcius":16,"relative_humidity":47.5,"windspeed_knots":5.4,"max_wind_speed":12.0,"precipitation ":" 0.00I"},{"station":948701,"date":"5\/04\/2017","air_temperature_celcius":17,"relative_humidity":47.2,"windspeed_knots":4.9,"max_wind_speed":13.0,"precipitation ":" 0.00I"},{"station":948701,"date":"6\/04\/2017","air_temperature_celcius":19,"relative_humidity":44.2,"windspeed_knots":7.8,"max_wind_speed":15.9,"precipitation ":" 0.00I"},{"station":948701,"date":"7\/04\/2017","air_temperature_celcius":21,"relative_humidity":47.0,"windspeed_knots":13.2,"max_wind_speed":20.0,"precipitation ":" 0.00I"},{"station":948701,"date":"8\/04\/2017","air_temperature_celcius":19,"relative_humidity":52.8,"windspeed_knots":12.5,"max_wind_speed":21.0,"precipitation ":" 0.47G"},{"station":948701,"date":"9\/04\/2017","air_temperature_celcius":11,"relative_humidity":48.2,"windspeed_knots":10.8,"max_wind_speed":22.9,"precipitation ":" 0.59G"},{"station":948701,"date":"10\/04\/2017","air_temperature_celcius":14,"relative_humidity":50.4,"windspeed_knots":12.8,"max_wind_speed":20.0,"precipitation ":" 0.01G"},{"station":948701,"date":"11\/04\/2017","air_temperature_celcius":14,"relative_humidity":52.5,"windspeed_knots":7.0,"max_wind_speed":13.0,"precipitation ":" 0.00G"},{"station":948701,"date":"12\/04\/2017","air_temperature_celcius":14,"relative_humidity":52.4,"windspeed_knots":6.7,"max_wind_speed":11.1,"precipitation ":" 0.00I"},{"station":948701,"date":"13\/04\/2017","air_temperature_celcius":16,"relative_humidity":54.9,"windspeed_knots":5.9,"max_wind_speed":9.9,"precipitation ":" 0.00I"},{"station":948701,"date":"14\/04\/2017","air_temperature_celcius":13,"relative_humidity":48.5,"windspeed_knots":5.3,"max_wind_speed":11.1,"precipitation ":" 0.08G"},{"station":948701,"date":"15\/04\/2017","air_temperature_celcius":12,"relative_humidity":44.0,"windspeed_knots":4.7,"max_wind_speed":7.0,"precipitation ":" 0.00G"},{"station":948701,"date":"16\/04\/2017","air_temperature_celcius":15,"relative_humidity":49.3,"windspeed_knots":3.6,"max_wind_speed":7.0,"precipitation ":" 0.00I"},{"station":948701,"date":"17\/04\/2017","air_temperature_celcius":13,"relative_humidity":51.4,"windspeed_knots":4.6,"max_wind_speed":8.9,"precipitation ":" 0.00I"},{"station":948701,"date":"18\/04\/2017","air_temperature_celcius":15,"relative_humidity":56.1,"windspeed_knots":5.1,"max_wind_speed":9.9,"precipitation ":" 0.00I"},{"station":948701,"date":"19\/04\/2017","air_temperature_celcius":22,"relative_humidity":52.8,"windspeed_knots":9.1,"max_wind_speed":15.0,"precipitation ":" 0.00I"},{"station":948701,"date":"20\/04\/2017","air_temperature_celcius":20,"relative_humidity":53.5,"windspeed_knots":7.2,"max_wind_speed":15.9,"precipitation ":" 0.31G"},{"station":948701,"date":"21\/04\/2017","air_temperature_celcius":17,"relative_humidity":58.1,"windspeed_knots":11.7,"max_wind_speed":19.0,"precipitation ":" 0.04G"},{"station":948701,"date":"22\/04\/2017","air_temperature_celcius":18,"relative_humidity":58.9,"windspeed_knots":5.5,"max_wind_speed":14.0,"precipitation ":" 0.08G"},{"station":948701,"date":"23\/04\/2017","air_temperature_celcius":17,"relative_humidity":59.3,"windspeed_knots":4.2,"max_wind_speed":7.0,"precipitation ":" 0.01G"},{"station":948701,"date":"24\/04\/2017","air_temperature_celcius":19,"relative_humidity":60.5,"windspeed_knots":7.0,"max_wind_speed":11.1,"precipitation ":" 0.83G"},{"station":948701,"date":"25\/04\/2017","air_temperature_celcius":14,"relative_humidity":52.8,"windspeed_knots":9.3,"max_wind_speed":18.1,"precipitation ":" 0.98G"},{"station":948701,"date":"26\/04\/2017","air_temperature_celcius":11,"relative_humidity":40.8,"windspeed_knots":12.2,"max_wind_speed":20.0,"precipitation ":" 0.24G"},{"station":948701,"date":"27\/04\/2017","air_temperature_celcius":12,"relative_humidity":48.2,"windspeed_knots":7.3,"max_wind_speed":11.1,"precipitation ":" 0.03G"},{"station":948701,"date":"28\/04\/2017","air_temperature_celcius":16,"relative_humidity":54.8,"windspeed_knots":8.3,"max_wind_speed":9.9,"precipitation ":" 0.00G"},{"station":948701,"date":"29\/04\/2017","air_temperature_celcius":15,"relative_humidity":51.9,"windspeed_knots":6.6,"max_wind_speed":12.0,"precipitation ":" 0.01G"},{"station":948701,"date":"30\/04\/2017","air_temperature_celcius":15,"relative_humidity":45.6,"windspeed_knots":10.2,"max_wind_speed":15.0,"precipitation ":" 0.00G"},{"station":948701,"date":"1\/05\/2017","air_temperature_celcius":14,"relative_humidity":49.2,"windspeed_knots":10.5,"max_wind_speed":20.0,"precipitation ":" 0.12G"},{"station":948701,"date":"2\/05\/2017","air_temperature_celcius":10,"relative_humidity":42.6,"windspeed_knots":8.9,"max_wind_speed":15.0,"precipitation ":" 0.04G"},{"station":948701,"date":"3\/05\/2017","air_temperature_celcius":10,"relative_humidity":43.1,"windspeed_knots":4.7,"max_wind_speed":8.0,"precipitation ":" 0.00G"},{"station":948701,"date":"4\/05\/2017","air_temperature_celcius":10,"relative_humidity":43.3,"windspeed_knots":2.6,"max_wind_speed":7.0,"precipitation ":" 0.00I"},{"station":948701,"date":"5\/05\/2017","air_temperature_celcius":14,"relative_humidity":47.4,"windspeed_knots":7.1,"max_wind_speed":14.0,"precipitation ":" 0.00I"},{"station":948701,"date":"6\/05\/2017","air_temperature_celcius":12,"relative_humidity":45.1,"windspeed_knots":11.9,"max_wind_speed":18.1,"precipitation ":" 0.16G"},{"station":948701,"date":"7\/05\/2017","air_temperature_celcius":12,"relative_humidity":45.0,"windspeed_knots":10.5,"max_wind_speed":16.9,"precipitation ":" 0.16G"},{"station":948701,"date":"8\/05\/2017","air_temperature_celcius":12,"relative_humidity":49.9,"windspeed_knots":6.1,"max_wind_speed":13.0,"precipitation ":" 0.02G"},{"station":948701,"date":"9\/05\/2017","air_temperature_celcius":12,"relative_humidity":49.0,"windspeed_knots":4.6,"max_wind_speed":8.9,"precipitation ":" 0.00G"},{"station":948701,"date":"10\/05\/2017","air_temperature_celcius":10,"relative_humidity":45.7,"windspeed_knots":3.7,"max_wind_speed":8.0,"precipitation ":" 0.01G"},{"station":948701,"date":"11\/05\/2017","air_temperature_celcius":9,"relative_humidity":45.3,"windspeed_knots":2.5,"max_wind_speed":6.0,"precipitation ":" 0.00G"},{"station":948701,"date":"12\/05\/2017","air_temperature_celcius":14,"relative_humidity":47.9,"windspeed_knots":5.3,"max_wind_speed":9.9,"precipitation ":" 0.00I"},{"station":948701,"date":"13\/05\/2017","air_temperature_celcius":9,"relative_humidity":44.0,"windspeed_knots":2.8,"max_wind_speed":8.0,"precipitation ":" 0.00I"},{"station":948701,"date":"14\/05\/2017","air_temperature_celcius":10,"relative_humidity":46.8,"windspeed_knots":5.3,"max_wind_speed":9.9,"precipitation ":" 0.00I"},{"station":948701,"date":"15\/05\/2017","air_temperature_celcius":10,"relative_humidity":47.0,"windspeed_knots":5.2,"max_wind_speed":8.9,"precipitation ":" 0.00I"},{"station":948701,"date":"16\/05\/2017","air_temperature_celcius":12,"relative_humidity":48.8,"windspeed_knots":4.2,"max_wind_speed":7.0,"precipitation ":" 0.00I"},{"station":948701,"date":"17\/05\/2017","air_temperature_celcius":13,"relative_humidity":49.4,"windspeed_knots":3.8,"max_wind_speed":9.9,"precipitation ":" 0.01G"},{"station":948701,"date":"18\/05\/2017","air_temperature_celcius":14,"relative_humidity":49.9,"windspeed_knots":6.8,"max_wind_speed":15.9,"precipitation ":" 0.00G"},{"station":948701,"date":"19\/05\/2017","air_temperature_celcius":12,"relative_humidity":51.6,"windspeed_knots":3.4,"max_wind_speed":11.1,"precipitation ":" 0.05G"},{"station":948701,"date":"20\/05\/2017","air_temperature_celcius":14,"relative_humidity":50.1,"windspeed_knots":8.7,"max_wind_speed":15.0,"precipitation ":" 0.00G"},{"station":948701,"date":"21\/05\/2017","air_temperature_celcius":14,"relative_humidity":51.0,"windspeed_knots":9.9,"max_wind_speed":15.0,"precipitation ":" 0.00I"},{"station":948701,"date":"22\/05\/2017","air_temperature_celcius":17,"relative_humidity":48.7,"windspeed_knots":10.5,"max_wind_speed":15.0,"precipitation ":" 0.00I"},{"station":948701,"date":"23\/05\/2017","air_temperature_celcius":15,"relative_humidity":49.9,"windspeed_knots":7.9,"max_wind_speed":13.0,"precipitation ":" 0.01G"},{"station":948701,"date":"24\/05\/2017","air_temperature_celcius":14,"relative_humidity":48.4,"windspeed_knots":7.5,"max_wind_speed":13.0,"precipitation ":" 0.00G"},{"station":948701,"date":"25\/05\/2017","air_temperature_celcius":14,"relative_humidity":50.7,"windspeed_knots":8.6,"max_wind_speed":13.0,"precipitation ":" 0.12G"},{"station":948701,"date":"26\/05\/2017","air_temperature_celcius":13,"relative_humidity":48.5,"windspeed_knots":7.1,"max_wind_speed":15.9,"precipitation ":" 0.00G"},{"station":948701,"date":"27\/05\/2017","air_temperature_celcius":14,"relative_humidity":48.1,"windspeed_knots":13.7,"max_wind_speed":19.0,"precipitation ":" 0.35G"},{"station":948701,"date":"28\/05\/2017","air_temperature_celcius":9,"relative_humidity":41.2,"windspeed_knots":10.0,"max_wind_speed":13.0,"precipitation ":" 0.02G"},{"station":948701,"date":"29\/05\/2017","air_temperature_celcius":12,"relative_humidity":42.8,"windspeed_knots":12.1,"max_wind_speed":19.0,"precipitation ":" 0.04G"},{"station":948701,"date":"30\/05\/2017","air_temperature_celcius":8,"relative_humidity":41.6,"windspeed_knots":8.3,"max_wind_speed":15.9,"precipitation ":" 0.24G"},{"station":948701,"date":"31\/05\/2017","air_temperature_celcius":11,"relative_humidity":43.8,"windspeed_knots":6.5,"max_wind_speed":12.0,"precipitation ":" 0.02G"},{"station":948701,"date":"1\/06\/2017","air_temperature_celcius":11,"relative_humidity":43.2,"windspeed_knots":5.5,"max_wind_speed":8.0,"precipitation ":" 0.00G"},{"station":948701,"date":"2\/06\/2017","air_temperature_celcius":12,"relative_humidity":47.0,"windspeed_knots":4.8,"max_wind_speed":8.9,"precipitation ":" 0.00I"},{"station":948701,"date":"3\/06\/2017","air_temperature_celcius":8,"relative_humidity":43.3,"windspeed_knots":3.9,"max_wind_speed":8.0,"precipitation ":" 0.00I"},{"station":948701,"date":"4\/06\/2017","air_temperature_celcius":9,"relative_humidity":43.2,"windspeed_knots":4.9,"max_wind_speed":8.0,"precipitation ":" 0.00I"},{"station":948701,"date":"5\/06\/2017","air_temperature_celcius":12,"relative_humidity":47.6,"windspeed_knots":9.1,"max_wind_speed":13.0,"precipitation ":" 0.12G"},{"station":948701,"date":"6\/06\/2017","air_temperature_celcius":9,"relative_humidity":40.8,"windspeed_knots":6.7,"max_wind_speed":15.0,"precipitation ":" 0.01G"},{"station":948701,"date":"7\/06\/2017","air_temperature_celcius":8,"relative_humidity":40.7,"windspeed_knots":5.3,"max_wind_speed":12.0,"precipitation ":" 0.00G"},{"station":948701,"date":"8\/06\/2017","air_temperature_celcius":10,"relative_humidity":46.3,"windspeed_knots":4.6,"max_wind_speed":8.0,"precipitation ":" 0.08G"},{"station":948701,"date":"9\/06\/2017","air_temperature_celcius":10,"relative_humidity":47.1,"windspeed_knots":4.6,"max_wind_speed":8.9,"precipitation ":" 0.00G"},{"station":948701,"date":"10\/06\/2017","air_temperature_celcius":8,"relative_humidity":44.5,"windspeed_knots":4.7,"max_wind_speed":7.0,"precipitation ":" 0.01G"},{"station":948701,"date":"11\/06\/2017","air_temperature_celcius":10,"relative_humidity":44.9,"windspeed_knots":5.5,"max_wind_speed":8.9,"precipitation ":" 0.00G"},{"station":948701,"date":"12\/06\/2017","air_temperature_celcius":12,"relative_humidity":49.4,"windspeed_knots":4.4,"max_wind_speed":8.9,"precipitation ":" 0.00I"},{"station":948701,"date":"13\/06\/2017","air_temperature_celcius":8,"relative_humidity":43.1,"windspeed_knots":3.4,"max_wind_speed":7.0,"precipitation ":" 0.00I"},{"station":948701,"date":"14\/06\/2017","air_temperature_celcius":11,"relative_humidity":46.4,"windspeed_knots":6.5,"max_wind_speed":8.9,"precipitation ":" 0.00I"},{"station":948701,"date":"15\/06\/2017","air_temperature_celcius":11,"relative_humidity":45.4,"windspeed_knots":5.2,"max_wind_speed":8.9,"precipitation ":" 0.00A"},{"station":948701,"date":"16\/06\/2017","air_temperature_celcius":8,"relative_humidity":42.6,"windspeed_knots":2.0,"max_wind_speed":6.0,"precipitation ":" 0.00I"},{"station":948701,"date":"17\/06\/2017","air_temperature_celcius":10,"relative_humidity":45.6,"windspeed_knots":4.5,"max_wind_speed":7.0,"precipitation ":" 0.00I"},{"station":948701,"date":"18\/06\/2017","air_temperature_celcius":10,"relative_humidity":47.9,"windspeed_knots":4.1,"max_wind_speed":7.0,"precipitation ":" 0.00I"},{"station":948701,"date":"19\/06\/2017","air_temperature_celcius":11,"relative_humidity":45.1,"windspeed_knots":5.6,"max_wind_speed":9.9,"precipitation ":" 0.00I"},{"station":948701,"date":"20\/06\/2017","air_temperature_celcius":11,"relative_humidity":45.3,"windspeed_knots":10.6,"max_wind_speed":16.9,"precipitation ":" 0.08G"},{"station":948701,"date":"21\/06\/2017","air_temperature_celcius":10,"relative_humidity":45.9,"windspeed_knots":3.2,"max_wind_speed":7.0,"precipitation ":" 0.00G"},{"station":948701,"date":"22\/06\/2017","air_temperature_celcius":10,"relative_humidity":41.4,"windspeed_knots":9.4,"max_wind_speed":14.0,"precipitation ":" 0.00I"},{"station":948701,"date":"23\/06\/2017","air_temperature_celcius":11,"relative_humidity":43.9,"windspeed_knots":11.2,"max_wind_speed":16.9,"precipitation ":" 0.12G"},{"station":948701,"date":"24\/06\/2017","air_temperature_celcius":10,"relative_humidity":37.9,"windspeed_knots":8.5,"max_wind_speed":14.0,"precipitation ":" 0.02G"},{"station":948701,"date":"25\/06\/2017","air_temperature_celcius":11,"relative_humidity":44.2,"windspeed_knots":8.7,"max_wind_speed":15.9,"precipitation ":" 0.04G"},{"station":948701,"date":"26\/06\/2017","air_temperature_celcius":10,"relative_humidity":45.7,"windspeed_knots":3.6,"max_wind_speed":7.0,"precipitation ":" 0.01G"},{"station":948701,"date":"27\/06\/2017","air_temperature_celcius":9,"relative_humidity":41.0,"windspeed_knots":8.2,"max_wind_speed":9.9,"precipitation ":" 0.00G"},{"station":948701,"date":"28\/06\/2017","air_temperature_celcius":10,"relative_humidity":43.7,"windspeed_knots":7.2,"max_wind_speed":11.1,"precipitation ":" 0.00I"},{"station":948701,"date":"29\/06\/2017","air_temperature_celcius":10,"relative_humidity":42.1,"windspeed_knots":9.4,"max_wind_speed":15.0,"precipitation ":" 0.13B"},{"station":948701,"date":"30\/06\/2017","air_temperature_celcius":5,"relative_humidity":34.9,"windspeed_knots":4.3,"max_wind_speed":11.1,"precipitation ":" 0.00A"},{"station":948701,"date":"1\/07\/2017","air_temperature_celcius":5,"relative_humidity":33.1,"windspeed_knots":5.8,"max_wind_speed":14.0,"precipitation ":" 0.00I"},{"station":948701,"date":"2\/07\/2017","air_temperature_celcius":6,"relative_humidity":30.8,"windspeed_knots":5.7,"max_wind_speed":11.1,"precipitation ":" 0.00I"},{"station":948701,"date":"3\/07\/2017","air_temperature_celcius":11,"relative_humidity":45.1,"windspeed_knots":11.5,"max_wind_speed":18.1,"precipitation ":" 0.20G"},{"station":948701,"date":"4\/07\/2017","air_temperature_celcius":12,"relative_humidity":47.2,"windspeed_knots":8.8,"max_wind_speed":15.0,"precipitation ":" 0.00G"},{"station":948701,"date":"5\/07\/2017","air_temperature_celcius":9,"relative_humidity":42.4,"windspeed_knots":7.2,"max_wind_speed":9.9,"precipitation ":" 0.00I"},{"station":948701,"date":"6\/07\/2017","air_temperature_celcius":9,"relative_humidity":40.1,"windspeed_knots":7.5,"max_wind_speed":11.1,"precipitation ":" 0.00I"},{"station":948701,"date":"7\/07\/2017","air_temperature_celcius":9,"relative_humidity":41.2,"windspeed_knots":9.8,"max_wind_speed":15.9,"precipitation ":" 0.00I"},{"station":948701,"date":"8\/07\/2017","air_temperature_celcius":9,"relative_humidity":42.8,"windspeed_knots":9.3,"max_wind_speed":13.0,"precipitation ":" 0.08G"},{"station":948701,"date":"9\/07\/2017","air_temperature_celcius":10,"relative_humidity":39.4,"windspeed_knots":9.6,"max_wind_speed":14.0,"precipitation ":" 0.00G"},{"station":948701,"date":"10\/07\/2017","air_temperature_celcius":10,"relative_humidity":44.4,"windspeed_knots":5.6,"max_wind_speed":11.1,"precipitation ":" 0.12G"},{"station":948701,"date":"11\/07\/2017","air_temperature_celcius":6,"relative_humidity":39.0,"windspeed_knots":1.8,"max_wind_speed":5.1,"precipitation ":" 0.01G"},{"station":948701,"date":"12\/07\/2017","air_temperature_celcius":9,"relative_humidity":39.0,"windspeed_knots":5.6,"max_wind_speed":8.9,"precipitation ":" 0.00G"},{"station":948701,"date":"13\/07\/2017","air_temperature_celcius":12,"relative_humidity":40.7,"windspeed_knots":16.7,"max_wind_speed":21.0,"precipitation ":" 0.12G"},{"station":948701,"date":"14\/07\/2017","air_temperature_celcius":9,"relative_humidity":40.0,"windspeed_knots":8.6,"max_wind_speed":15.0,"precipitation ":" 0.00G"},{"station":948701,"date":"15\/07\/2017","air_temperature_celcius":6,"relative_humidity":37.1,"windspeed_knots":5.8,"max_wind_speed":9.9,"precipitation ":" 0.00I"},{"station":948701,"date":"16\/07\/2017","air_temperature_celcius":10,"relative_humidity":35.6,"windspeed_knots":14.5,"max_wind_speed":20.0,"precipitation ":" 0.00I"},{"station":948701,"date":"17\/07\/2017","air_temperature_celcius":12,"relative_humidity":41.8,"windspeed_knots":14.7,"max_wind_speed":21.0,"precipitation ":" 0.00I"},{"station":948701,"date":"18\/07\/2017","air_temperature_celcius":10,"relative_humidity":44.8,"windspeed_knots":8.8,"max_wind_speed":14.0,"precipitation ":" 0.39G"},{"station":948701,"date":"19\/07\/2017","air_temperature_celcius":10,"relative_humidity":43.5,"windspeed_knots":12.0,"max_wind_speed":16.9,"precipitation ":" 0.04G"},{"station":948701,"date":"20\/07\/2017","air_temperature_celcius":7,"relative_humidity":40.5,"windspeed_knots":8.1,"max_wind_speed":15.0,"precipitation ":" 0.12G"},{"station":948701,"date":"21\/07\/2017","air_temperature_celcius":8,"relative_humidity":39.3,"windspeed_knots":7.7,"max_wind_speed":14.0,"precipitation ":" 0.00G"},{"station":948701,"date":"22\/07\/2017","air_temperature_celcius":11,"relative_humidity":35.3,"windspeed_knots":18.2,"max_wind_speed":25.1,"precipitation ":" 0.00I"},{"station":948701,"date":"23\/07\/2017","air_temperature_celcius":10,"relative_humidity":44.7,"windspeed_knots":8.0,"max_wind_speed":15.9,"precipitation ":" 0.08G"},{"station":948701,"date":"24\/07\/2017","air_temperature_celcius":12,"relative_humidity":44.7,"windspeed_knots":11.4,"max_wind_speed":18.1,"precipitation ":" 0.00G"},{"station":948701,"date":"25\/07\/2017","air_temperature_celcius":13,"relative_humidity":44.0,"windspeed_knots":13.6,"max_wind_speed":21.0,"precipitation ":" 0.04G"},{"station":948701,"date":"26\/07\/2017","air_temperature_celcius":8,"relative_humidity":43.8,"windspeed_knots":7.3,"max_wind_speed":14.0,"precipitation ":" 0.08G"},{"station":948701,"date":"27\/07\/2017","air_temperature_celcius":11,"relative_humidity":43.5,"windspeed_knots":13.1,"max_wind_speed":21.0,"precipitation ":" 0.24G"},{"station":948701,"date":"28\/07\/2017","air_temperature_celcius":11,"relative_humidity":40.5,"windspeed_knots":13.4,"max_wind_speed":26.0,"precipitation ":" 0.00G"},{"station":948701,"date":"29\/07\/2017","air_temperature_celcius":15,"relative_humidity":41.5,"windspeed_knots":17.0,"max_wind_speed":28.9,"precipitation ":" 0.00I"},{"station":948701,"date":"30\/07\/2017","air_temperature_celcius":9,"relative_humidity":42.0,"windspeed_knots":4.6,"max_wind_speed":12.0,"precipitation ":" 0.00I"},{"station":948701,"date":"31\/07\/2017","air_temperature_celcius":7,"relative_humidity":40.5,"windspeed_knots":3.1,"max_wind_speed":8.0,"precipitation ":" 0.00I"},{"station":948701,"date":"1\/08\/2017","air_temperature_celcius":7,"relative_humidity":40.7,"windspeed_knots":3.7,"max_wind_speed":7.0,"precipitation ":" 0.00I"},{"station":948701,"date":"2\/08\/2017","air_temperature_celcius":5,"relative_humidity":38.6,"windspeed_knots":1.8,"max_wind_speed":5.1,"precipitation ":" 0.00I"},{"station":948701,"date":"3\/08\/2017","air_temperature_celcius":8,"relative_humidity":44.6,"windspeed_knots":3.9,"max_wind_speed":8.0,"precipitation ":" 0.39G"},{"station":948702,"date":"4\/08\/2017","air_temperature_celcius":10,"relative_humidity":41.0,"windspeed_knots":14.1,"max_wind_speed":20.0,"precipitation ":" 0.02G"},{"station":948702,"date":"5\/08\/2017","air_temperature_celcius":11,"relative_humidity":40.4,"windspeed_knots":19.3,"max_wind_speed":26.0,"precipitation ":" 0.00G"},{"station":948702,"date":"6\/08\/2017","air_temperature_celcius":9,"relative_humidity":41.1,"windspeed_knots":12.7,"max_wind_speed":19.0,"precipitation ":" 0.24G"},{"station":948702,"date":"7\/08\/2017","air_temperature_celcius":9,"relative_humidity":42.9,"windspeed_knots":8.9,"max_wind_speed":15.9,"precipitation ":" 0.12G"},{"station":948702,"date":"8\/08\/2017","air_temperature_celcius":12,"relative_humidity":44.9,"windspeed_knots":7.9,"max_wind_speed":11.1,"precipitation ":" 0.00G"},{"station":948702,"date":"9\/08\/2017","air_temperature_celcius":14,"relative_humidity":43.7,"windspeed_knots":17.0,"max_wind_speed":27.0,"precipitation ":" 0.00I"},{"station":948702,"date":"10\/08\/2017","air_temperature_celcius":15,"relative_humidity":41.6,"windspeed_knots":15.0,"max_wind_speed":28.0,"precipitation ":" 0.00I"},{"station":948702,"date":"11\/08\/2017","air_temperature_celcius":12,"relative_humidity":43.9,"windspeed_knots":12.0,"max_wind_speed":15.9,"precipitation ":" 0.08G"},{"station":948702,"date":"12\/08\/2017","air_temperature_celcius":12,"relative_humidity":47.0,"windspeed_knots":7.7,"max_wind_speed":15.0,"precipitation ":" 0.08G"},{"station":948702,"date":"13\/08\/2017","air_temperature_celcius":15,"relative_humidity":41.2,"windspeed_knots":13.8,"max_wind_speed":16.9,"precipitation ":" 0.00G"},{"station":948702,"date":"14\/08\/2017","air_temperature_celcius":14,"relative_humidity":44.6,"windspeed_knots":7.7,"max_wind_speed":15.9,"precipitation ":" 0.03G"},{"station":948702,"date":"15\/08\/2017","air_temperature_celcius":14,"relative_humidity":49.9,"windspeed_knots":13.7,"max_wind_speed":22.0,"precipitation ":" 0.03G"},{"station":948702,"date":"16\/08\/2017","air_temperature_celcius":13,"relative_humidity":42.5,"windspeed_knots":14.0,"max_wind_speed":19.0,"precipitation ":" 0.04G"},{"station":948702,"date":"17\/08\/2017","air_temperature_celcius":10,"relative_humidity":39.9,"windspeed_knots":12.6,"max_wind_speed":16.9,"precipitation ":" 0.08G"},{"station":948702,"date":"18\/08\/2017","air_temperature_celcius":8,"relative_humidity":41.0,"windspeed_knots":11.0,"max_wind_speed":16.9,"precipitation ":" 0.47G"},{"station":948702,"date":"19\/08\/2017","air_temperature_celcius":7,"relative_humidity":37.9,"windspeed_knots":5.7,"max_wind_speed":9.9,"precipitation ":" 0.04G"},{"station":948702,"date":"20\/08\/2017","air_temperature_celcius":8,"relative_humidity":37.2,"windspeed_knots":5.5,"max_wind_speed":11.1,"precipitation ":" 0.00G"},{"station":948702,"date":"21\/08\/2017","air_temperature_celcius":9,"relative_humidity":40.4,"windspeed_knots":6.9,"max_wind_speed":9.9,"precipitation ":" 0.02G"},{"station":948702,"date":"22\/08\/2017","air_temperature_celcius":12,"relative_humidity":43.3,"windspeed_knots":7.0,"max_wind_speed":11.1,"precipitation ":" 0.00G"},{"station":948702,"date":"23\/08\/2017","air_temperature_celcius":10,"relative_humidity":44.1,"windspeed_knots":7.3,"max_wind_speed":12.0,"precipitation ":" 0.39G"},{"station":948702,"date":"24\/08\/2017","air_temperature_celcius":9,"relative_humidity":42.2,"windspeed_knots":6.4,"max_wind_speed":9.9,"precipitation ":" 0.01G"},{"station":948702,"date":"25\/08\/2017","air_temperature_celcius":12,"relative_humidity":40.4,"windspeed_knots":5.9,"max_wind_speed":8.9,"precipitation ":" 0.00G"},{"station":948702,"date":"26\/08\/2017","air_temperature_celcius":11,"relative_humidity":39.7,"windspeed_knots":11.8,"max_wind_speed":19.0,"precipitation ":" 0.28G"},{"station":948702,"date":"27\/08\/2017","air_temperature_celcius":7,"relative_humidity":37.2,"windspeed_knots":6.2,"max_wind_speed":16.9,"precipitation ":" 0.08G"},{"station":948702,"date":"28\/08\/2017","air_temperature_celcius":8,"relative_humidity":40.8,"windspeed_knots":5.5,"max_wind_speed":9.9,"precipitation ":" 0.01G"},{"station":948702,"date":"29\/08\/2017","air_temperature_celcius":10,"relative_humidity":41.4,"windspeed_knots":6.9,"max_wind_speed":8.9,"precipitation ":" 0.00G"},{"station":948702,"date":"30\/08\/2017","air_temperature_celcius":8,"relative_humidity":39.3,"windspeed_knots":4.7,"max_wind_speed":13.0,"precipitation ":" 0.02G"},{"station":948702,"date":"31\/08\/2017","air_temperature_celcius":8,"relative_humidity":36.3,"windspeed_knots":6.3,"max_wind_speed":13.0,"precipitation ":" 0.01G"},{"station":948702,"date":"1\/09\/2017","air_temperature_celcius":13,"relative_humidity":38.4,"windspeed_knots":11.5,"max_wind_speed":16.9,"precipitation ":" 0.00G"},{"station":948702,"date":"2\/09\/2017","air_temperature_celcius":17,"relative_humidity":38.7,"windspeed_knots":16.8,"max_wind_speed":22.9,"precipitation ":" 0.00I"},{"station":948702,"date":"3\/09\/2017","air_temperature_celcius":12,"relative_humidity":41.0,"windspeed_knots":12.9,"max_wind_speed":16.9,"precipitation ":" 0.16G"},{"station":948702,"date":"4\/09\/2017","air_temperature_celcius":8,"relative_humidity":35.0,"windspeed_knots":14.4,"max_wind_speed":20.0,"precipitation ":" 0.00G"},{"station":948702,"date":"5\/09\/2017","air_temperature_celcius":8,"relative_humidity":38.6,"windspeed_knots":12.8,"max_wind_speed":18.1,"precipitation ":" 0.31G"},{"station":948702,"date":"6\/09\/2017","air_temperature_celcius":10,"relative_humidity":43.7,"windspeed_knots":9.5,"max_wind_speed":13.0,"precipitation ":" 0.08G"},{"station":948702,"date":"7\/09\/2017","air_temperature_celcius":10,"relative_humidity":43.6,"windspeed_knots":9.7,"max_wind_speed":14.0,"precipitation ":" 0.20G"},{"station":948702,"date":"8\/09\/2017","air_temperature_celcius":9,"relative_humidity":41.9,"windspeed_knots":9.2,"max_wind_speed":14.0,"precipitation ":" 0.12G"},{"station":948702,"date":"9\/09\/2017","air_temperature_celcius":9,"relative_humidity":43.9,"windspeed_knots":5.7,"max_wind_speed":9.9,"precipitation ":" 0.00G"},{"station":948702,"date":"10\/09\/2017","air_temperature_celcius":11,"relative_humidity":41.7,"windspeed_knots":8.7,"max_wind_speed":19.0,"precipitation ":" 0.00I"},{"station":948702,"date":"11\/09\/2017","air_temperature_celcius":14,"relative_humidity":47.4,"windspeed_knots":10.6,"max_wind_speed":19.0,"precipitation ":" 0.03G"},{"station":948702,"date":"12\/09\/2017","air_temperature_celcius":13,"relative_humidity":51.1,"windspeed_knots":6.0,"max_wind_speed":13.0,"precipitation ":" 0.12G"},{"station":948702,"date":"13\/09\/2017","air_temperature_celcius":9,"relative_humidity":40.1,"windspeed_knots":12.1,"max_wind_speed":15.0,"precipitation ":" 0.08G"},{"station":948702,"date":"14\/09\/2017","air_temperature_celcius":12,"relative_humidity":44.5,"windspeed_knots":11.1,"max_wind_speed":15.0,"precipitation ":" 0.00G"},{"station":948702,"date":"15\/09\/2017","air_temperature_celcius":11,"relative_humidity":46.2,"windspeed_knots":10.5,"max_wind_speed":15.0,"precipitation ":" 0.28G"},{"station":948702,"date":"16\/09\/2017","air_temperature_celcius":9,"relative_humidity":37.9,"windspeed_knots":9.1,"max_wind_speed":15.9,"precipitation ":" 0.00G"},{"station":948702,"date":"17\/09\/2017","air_temperature_celcius":14,"relative_humidity":36.0,"windspeed_knots":15.9,"max_wind_speed":22.0,"precipitation ":" 0.00I"},{"station":948702,"date":"18\/09\/2017","air_temperature_celcius":14,"relative_humidity":39.3,"windspeed_knots":17.7,"max_wind_speed":30.9,"precipitation ":" 0.01G"},{"station":948702,"date":"19\/09\/2017","air_temperature_celcius":9,"relative_humidity":41.2,"windspeed_knots":6.7,"max_wind_speed":13.0,"precipitation ":" 0.01G"},{"station":948702,"date":"20\/09\/2017","air_temperature_celcius":14,"relative_humidity":41.7,"windspeed_knots":12.3,"max_wind_speed":18.1,"precipitation ":" 0.00G"},{"station":948702,"date":"21\/09\/2017","air_temperature_celcius":15,"relative_humidity":47.3,"windspeed_knots":8.6,"max_wind_speed":22.9,"precipitation ":" 0.00I"},{"station":948702,"date":"22\/09\/2017","air_temperature_celcius":20,"relative_humidity":43.6,"windspeed_knots":10.3,"max_wind_speed":15.0,"precipitation ":" 0.00I"},{"station":948702,"date":"23\/09\/2017","air_temperature_celcius":17,"relative_humidity":46.3,"windspeed_knots":11.7,"max_wind_speed":20.0,"precipitation ":" 0.02G"},{"station":948702,"date":"24\/09\/2017","air_temperature_celcius":14,"relative_humidity":44.0,"windspeed_knots":14.4,"max_wind_speed":23.9,"precipitation ":" 0.16G"},{"station":948702,"date":"25\/09\/2017","air_temperature_celcius":9,"relative_humidity":42.1,"windspeed_knots":7.6,"max_wind_speed":12.0,"precipitation ":" 0.01G"},{"station":948702,"date":"26\/09\/2017","air_temperature_celcius":11,"relative_humidity":40.8,"windspeed_knots":6.4,"max_wind_speed":8.9,"precipitation ":" 0.00G"},{"station":948702,"date":"27\/09\/2017","air_temperature_celcius":15,"relative_humidity":44.8,"windspeed_knots":8.3,"max_wind_speed":19.0,"precipitation ":" 0.00I"},{"station":948702,"date":"28\/09\/2017","air_temperature_celcius":13,"relative_humidity":43.6,"windspeed_knots":9.0,"max_wind_speed":15.0,"precipitation ":" 0.00I"},{"station":948702,"date":"29\/09\/2017","air_temperature_celcius":14,"relative_humidity":41.6,"windspeed_knots":13.1,"max_wind_speed":18.1,"precipitation ":" 0.00I"},{"station":948702,"date":"30\/09\/2017","air_temperature_celcius":11,"relative_humidity":41.6,"windspeed_knots":7.9,"max_wind_speed":15.0,"precipitation ":" 0.01G"},{"station":948702,"date":"1\/10\/2017","air_temperature_celcius":12,"relative_humidity":47.9,"windspeed_knots":6.7,"max_wind_speed":11.1,"precipitation ":" 0.00G"},{"station":948702,"date":"2\/10\/2017","air_temperature_celcius":11,"relative_humidity":44.2,"windspeed_knots":5.8,"max_wind_speed":9.9,"precipitation ":" 0.00I"},{"station":948702,"date":"3\/10\/2017","air_temperature_celcius":13,"relative_humidity":46.2,"windspeed_knots":5.6,"max_wind_speed":12.0,"precipitation ":" 0.00I"},{"station":948702,"date":"4\/10\/2017","air_temperature_celcius":19,"relative_humidity":50.3,"windspeed_knots":7.7,"max_wind_speed":11.1,"precipitation ":" 0.00I"},{"station":948702,"date":"5\/10\/2017","air_temperature_celcius":12,"relative_humidity":47.5,"windspeed_knots":15.0,"max_wind_speed":18.1,"precipitation ":" 0.20G"},{"station":948702,"date":"6\/10\/2017","air_temperature_celcius":11,"relative_humidity":45.3,"windspeed_knots":8.5,"max_wind_speed":15.0,"precipitation ":" 0.00G"},{"station":948702,"date":"7\/10\/2017","air_temperature_celcius":17,"relative_humidity":46.4,"windspeed_knots":9.5,"max_wind_speed":20.0,"precipitation ":" 0.00I"},{"station":948702,"date":"8\/10\/2017","air_temperature_celcius":18,"relative_humidity":54.6,"windspeed_knots":12.0,"max_wind_speed":25.1,"precipitation ":" 0.12G"},{"station":948702,"date":"9\/10\/2017","air_temperature_celcius":12,"relative_humidity":44.4,"windspeed_knots":7.8,"max_wind_speed":14.0,"precipitation ":" 0.00G"},{"station":948702,"date":"10\/10\/2017","air_temperature_celcius":13,"relative_humidity":42.5,"windspeed_knots":8.0,"max_wind_speed":15.0,"precipitation ":" 0.00I"},{"station":948702,"date":"11\/10\/2017","air_temperature_celcius":15,"relative_humidity":48.2,"windspeed_knots":14.7,"max_wind_speed":25.1,"precipitation ":" 0.43G"},{"station":948702,"date":"12\/10\/2017","air_temperature_celcius":15,"relative_humidity":44.5,"windspeed_knots":10.2,"max_wind_speed":14.0,"precipitation ":" 0.00G"},{"station":948702,"date":"13\/10\/2017","air_temperature_celcius":12,"relative_humidity":44.2,"windspeed_knots":6.2,"max_wind_speed":15.0,"precipitation ":" 0.00I"},{"station":948702,"date":"14\/10\/2017","air_temperature_celcius":11,"relative_humidity":43.2,"windspeed_knots":5.9,"max_wind_speed":14.0,"precipitation ":" 0.00I"},{"station":948702,"date":"15\/10\/2017","air_temperature_celcius":13,"relative_humidity":50.7,"windspeed_knots":6.1,"max_wind_speed":13.0,"precipitation ":" 0.00I"},{"station":948702,"date":"16\/10\/2017","air_temperature_celcius":19,"relative_humidity":54.3,"windspeed_knots":5.9,"max_wind_speed":12.0,"precipitation ":" 0.00I"},{"station":948702,"date":"17\/10\/2017","air_temperature_celcius":22,"relative_humidity":46.8,"windspeed_knots":8.0,"max_wind_speed":16.9,"precipitation ":" 0.00I"},{"station":948702,"date":"18\/10\/2017","air_temperature_celcius":26,"relative_humidity":52.2,"windspeed_knots":13.7,"max_wind_speed":16.9,"precipitation ":" 0.00I"},{"station":948702,"date":"19\/10\/2017","air_temperature_celcius":15,"relative_humidity":51.0,"windspeed_knots":9.6,"max_wind_speed":15.9,"precipitation ":" 0.16G"},{"station":948702,"date":"20\/10\/2017","air_temperature_celcius":13,"relative_humidity":42.0,"windspeed_knots":11.4,"max_wind_speed":16.9,"precipitation ":" 0.00G"},{"station":948702,"date":"21\/10\/2017","air_temperature_celcius":12,"relative_humidity":47.3,"windspeed_knots":9.7,"max_wind_speed":14.0,"precipitation ":" 0.02G"},{"station":948702,"date":"22\/10\/2017","air_temperature_celcius":13,"relative_humidity":50.3,"windspeed_knots":8.6,"max_wind_speed":13.0,"precipitation ":" 0.02G"},{"station":948702,"date":"23\/10\/2017","air_temperature_celcius":14,"relative_humidity":49.5,"windspeed_knots":6.0,"max_wind_speed":12.0,"precipitation ":" 0.00G"},{"station":948702,"date":"24\/10\/2017","air_temperature_celcius":15,"relative_humidity":53.7,"windspeed_knots":6.8,"max_wind_speed":11.1,"precipitation ":" 0.51G"},{"station":948702,"date":"25\/10\/2017","air_temperature_celcius":14,"relative_humidity":51.0,"windspeed_knots":9.1,"max_wind_speed":12.0,"precipitation ":" 0.00G"},{"station":948702,"date":"26\/10\/2017","air_temperature_celcius":13,"relative_humidity":50.4,"windspeed_knots":7.9,"max_wind_speed":14.0,"precipitation ":" 0.00I"},{"station":948702,"date":"27\/10\/2017","air_temperature_celcius":22,"relative_humidity":46.9,"windspeed_knots":12.9,"max_wind_speed":19.0,"precipitation ":" 0.00I"},{"station":948702,"date":"28\/10\/2017","air_temperature_celcius":15,"relative_humidity":48.7,"windspeed_knots":8.5,"max_wind_speed":20.0,"precipitation ":" 0.01G"},{"station":948702,"date":"29\/10\/2017","air_temperature_celcius":17,"relative_humidity":44.9,"windspeed_knots":16.1,"max_wind_speed":27.0,"precipitation ":" 0.24G"},{"station":948702,"date":"30\/10\/2017","air_temperature_celcius":11,"relative_humidity":43.2,"windspeed_knots":8.1,"max_wind_speed":14.0,"precipitation ":" 0.20G"},{"station":948702,"date":"31\/10\/2017","air_temperature_celcius":13,"relative_humidity":47.1,"windspeed_knots":8.1,"max_wind_speed":12.0,"precipitation ":" 0.01G"},{"station":948702,"date":"1\/11\/2017","air_temperature_celcius":13,"relative_humidity":50.1,"windspeed_knots":8.5,"max_wind_speed":12.0,"precipitation ":" 0.08G"},{"station":948702,"date":"2\/11\/2017","air_temperature_celcius":12,"relative_humidity":43.8,"windspeed_knots":6.7,"max_wind_speed":14.0,"precipitation ":" 0.16G"},{"station":948702,"date":"3\/11\/2017","air_temperature_celcius":11,"relative_humidity":40.4,"windspeed_knots":9.2,"max_wind_speed":15.0,"precipitation ":" 0.04G"},{"station":948702,"date":"4\/11\/2017","air_temperature_celcius":11,"relative_humidity":41.4,"windspeed_knots":7.7,"max_wind_speed":15.0,"precipitation ":" 0.03G"},{"station":948702,"date":"5\/11\/2017","air_temperature_celcius":13,"relative_humidity":43.3,"windspeed_knots":9.4,"max_wind_speed":14.0,"precipitation ":" 0.00G"},{"station":948702,"date":"6\/11\/2017","air_temperature_celcius":13,"relative_humidity":44.1,"windspeed_knots":12.9,"max_wind_speed":19.0,"precipitation ":" 0.02G"},{"station":948702,"date":"7\/11\/2017","air_temperature_celcius":12,"relative_humidity":42.7,"windspeed_knots":10.0,"max_wind_speed":15.9,"precipitation ":" 0.01G"},{"station":948702,"date":"8\/11\/2017","air_temperature_celcius":12,"relative_humidity":46.6,"windspeed_knots":6.7,"max_wind_speed":14.0,"precipitation ":" 0.00G"},{"station":948702,"date":"9\/11\/2017","air_temperature_celcius":14,"relative_humidity":50.9,"windspeed_knots":5.9,"max_wind_speed":13.0,"precipitation ":" 0.00I"},{"station":948702,"date":"10\/11\/2017","air_temperature_celcius":18,"relative_humidity":53.8,"windspeed_knots":6.4,"max_wind_speed":11.1,"precipitation ":" 0.00I"},{"station":948702,"date":"11\/11\/2017","air_temperature_celcius":18,"relative_humidity":55.6,"windspeed_knots":8.2,"max_wind_speed":12.0,"precipitation ":" 0.00I"},{"station":948702,"date":"12\/11\/2017","air_temperature_celcius":18,"relative_humidity":53.8,"windspeed_knots":6.7,"max_wind_speed":14.0,"precipitation ":" 0.00I"},{"station":948702,"date":"13\/11\/2017","air_temperature_celcius":24,"relative_humidity":51.9,"windspeed_knots":7.3,"max_wind_speed":13.0,"precipitation ":" 0.00I"},{"station":948702,"date":"14\/11\/2017","air_temperature_celcius":28,"relative_humidity":48.3,"windspeed_knots":11.9,"max_wind_speed":22.0,"precipitation ":" 0.00I"},{"station":948702,"date":"15\/11\/2017","air_temperature_celcius":21,"relative_humidity":58.8,"windspeed_knots":8.8,"max_wind_speed":22.9,"precipitation ":" 0.08G"},{"station":948702,"date":"16\/11\/2017","air_temperature_celcius":18,"relative_humidity":61.5,"windspeed_knots":5.5,"max_wind_speed":11.1,"precipitation ":" 0.28G"},{"station":948702,"date":"17\/11\/2017","air_temperature_celcius":19,"relative_humidity":58.7,"windspeed_knots":5.5,"max_wind_speed":12.0,"precipitation ":" 0.28G"},{"station":948702,"date":"18\/11\/2017","air_temperature_celcius":20,"relative_humidity":58.4,"windspeed_knots":4.7,"max_wind_speed":11.1,"precipitation ":" 0.01G"},{"station":948702,"date":"19\/11\/2017","air_temperature_celcius":22,"relative_humidity":57.0,"windspeed_knots":8.5,"max_wind_speed":15.0,"precipitation ":" 0.00G"},{"station":948702,"date":"20\/11\/2017","air_temperature_celcius":24,"relative_humidity":55.5,"windspeed_knots":7.9,"max_wind_speed":15.0,"precipitation ":" 0.00I"},{"station":948702,"date":"21\/11\/2017","air_temperature_celcius":24,"relative_humidity":51.8,"windspeed_knots":7.9,"max_wind_speed":15.0,"precipitation ":" 0.00I"},{"station":948702,"date":"22\/11\/2017","air_temperature_celcius":23,"relative_humidity":49.6,"windspeed_knots":6.3,"max_wind_speed":13.0,"precipitation ":" 0.00I"},{"station":948702,"date":"23\/11\/2017","air_temperature_celcius":24,"relative_humidity":56.8,"windspeed_knots":5.7,"max_wind_speed":9.9,"precipitation ":" 0.00I"},{"station":948702,"date":"24\/11\/2017","air_temperature_celcius":23,"relative_humidity":58.8,"windspeed_knots":9.1,"max_wind_speed":15.0,"precipitation ":" 0.01G"},{"station":948702,"date":"25\/11\/2017","air_temperature_celcius":24,"relative_humidity":60.1,"windspeed_knots":8.0,"max_wind_speed":13.0,"precipitation ":" 0.12G"},{"station":948702,"date":"26\/11\/2017","air_temperature_celcius":20,"relative_humidity":60.8,"windspeed_knots":10.4,"max_wind_speed":16.9,"precipitation ":" 0.08G"},{"station":948702,"date":"27\/11\/2017","air_temperature_celcius":17,"relative_humidity":52.7,"windspeed_knots":7.7,"max_wind_speed":14.0,"precipitation ":" 0.00G"},{"station":948702,"date":"28\/11\/2017","air_temperature_celcius":23,"relative_humidity":58.8,"windspeed_knots":8.8,"max_wind_speed":15.0,"precipitation ":" 0.00I"},{"station":948702,"date":"29\/11\/2017","air_temperature_celcius":28,"relative_humidity":56.7,"windspeed_knots":9.3,"max_wind_speed":16.9,"precipitation ":" 0.00I"},{"station":948702,"date":"30\/11\/2017","air_temperature_celcius":26,"relative_humidity":61.0,"windspeed_knots":9.3,"max_wind_speed":15.0,"precipitation ":" 0.20G"},{"station":948702,"date":"1\/12\/2017","air_temperature_celcius":17,"relative_humidity":59.0,"windspeed_knots":9.4,"max_wind_speed":15.0,"precipitation ":" 0.75G"},{"station":948702,"date":"2\/12\/2017","air_temperature_celcius":15,"relative_humidity":56.2,"windspeed_knots":16.9,"max_wind_speed":20.0,"precipitation ":" 1.77G"},{"station":948702,"date":"3\/12\/2017","air_temperature_celcius":14,"relative_humidity":48.2,"windspeed_knots":12.5,"max_wind_speed":19.0,"precipitation ":" 0.03G"},{"station":948702,"date":"4\/12\/2017","air_temperature_celcius":14,"relative_humidity":48.2,"windspeed_knots":9.1,"max_wind_speed":15.0,"precipitation ":" 0.00G"},{"station":948702,"date":"5\/12\/2017","air_temperature_celcius":17,"relative_humidity":53.0,"windspeed_knots":14.6,"max_wind_speed":22.9,"precipitation ":" 0.00I"},{"station":948702,"date":"6\/12\/2017","air_temperature_celcius":16,"relative_humidity":51.7,"windspeed_knots":7.4,"max_wind_speed":15.0,"precipitation ":" 0.00I"},{"station":948702,"date":"7\/12\/2017","air_temperature_celcius":15,"relative_humidity":51.0,"windspeed_knots":9.0,"max_wind_speed":13.0,"precipitation ":" 1.26G"},{"station":948702,"date":"8\/12\/2017","air_temperature_celcius":15,"relative_humidity":48.1,"windspeed_knots":7.9,"max_wind_speed":12.0,"precipitation ":" 0.00G"},{"station":948702,"date":"9\/12\/2017","air_temperature_celcius":17,"relative_humidity":53.6,"windspeed_knots":7.6,"max_wind_speed":15.0,"precipitation ":" 0.00I"},{"station":948702,"date":"10\/12\/2017","air_temperature_celcius":17,"relative_humidity":53.5,"windspeed_knots":7.3,"max_wind_speed":14.0,"precipitation ":" 0.00I"},{"station":948702,"date":"11\/12\/2017","air_temperature_celcius":17,"relative_humidity":52.0,"windspeed_knots":8.8,"max_wind_speed":15.0,"precipitation ":" 0.00I"},{"station":948702,"date":"12\/12\/2017","air_temperature_celcius":19,"relative_humidity":55.3,"windspeed_knots":6.2,"max_wind_speed":12.0,"precipitation ":" 0.00I"},{"station":948702,"date":"13\/12\/2017","air_temperature_celcius":28,"relative_humidity":49.9,"windspeed_knots":11.0,"max_wind_speed":19.0,"precipitation ":" 0.00I"},{"station":948702,"date":"14\/12\/2017","air_temperature_celcius":17,"relative_humidity":52.5,"windspeed_knots":7.7,"max_wind_speed":16.9,"precipitation ":" 0.00I"},{"station":948702,"date":"15\/12\/2017","air_temperature_celcius":18,"relative_humidity":52.0,"windspeed_knots":7.1,"max_wind_speed":14.0,"precipitation ":" 0.00I"},{"station":948702,"date":"16\/12\/2017","air_temperature_celcius":18,"relative_humidity":53.7,"windspeed_knots":9.0,"max_wind_speed":13.0,"precipitation ":" 0.00I"},{"station":948702,"date":"17\/12\/2017","air_temperature_celcius":21,"relative_humidity":58.7,"windspeed_knots":7.8,"max_wind_speed":13.0,"precipitation ":" 0.00I"},{"station":948702,"date":"18\/12\/2017","air_temperature_celcius":25,"relative_humidity":60.9,"windspeed_knots":6.3,"max_wind_speed":8.9,"precipitation ":" 0.00I"},{"station":948702,"date":"19\/12\/2017","air_temperature_celcius":21,"relative_humidity":57.4,"windspeed_knots":10.7,"max_wind_speed":22.9,"precipitation ":" 0.67G"},{"station":948702,"date":"20\/12\/2017","air_temperature_celcius":17,"relative_humidity":51.2,"windspeed_knots":9.9,"max_wind_speed":18.1,"precipitation ":" 0.00G"},{"station":948702,"date":"21\/12\/2017","air_temperature_celcius":17,"relative_humidity":52.5,"windspeed_knots":5.7,"max_wind_speed":11.1,"precipitation ":" 0.00I"},{"station":948702,"date":"22\/12\/2017","air_temperature_celcius":19,"relative_humidity":55.8,"windspeed_knots":6.0,"max_wind_speed":11.1,"precipitation ":" 0.00I"},{"station":948702,"date":"23\/12\/2017","air_temperature_celcius":19,"relative_humidity":53.9,"windspeed_knots":8.3,"max_wind_speed":14.0,"precipitation ":" 0.00I"},{"station":948702,"date":"24\/12\/2017","air_temperature_celcius":16,"relative_humidity":47.0,"windspeed_knots":12.0,"max_wind_speed":16.9,"precipitation ":" 0.00I"},{"station":948702,"date":"25\/12\/2017","air_temperature_celcius":17,"relative_humidity":50.4,"windspeed_knots":10.8,"max_wind_speed":16.9,"precipitation ":" 0.00I"},{"station":948702,"date":"26\/12\/2017","air_temperature_celcius":22,"relative_humidity":55.5,"windspeed_knots":10.3,"max_wind_speed":19.0,"precipitation ":" 0.00I"},{"station":948702,"date":"27\/12\/2017","air_temperature_celcius":28,"relative_humidity":58.3,"windspeed_knots":9.3,"max_wind_speed":15.9,"precipitation ":" 0.00I"},{"station":948702,"date":"28\/12\/2017","air_temperature_celcius":21,"relative_humidity":61.1,"windspeed_knots":6.6,"max_wind_speed":11.1,"precipitation ":" 0.00I"},{"station":948702,"date":"29\/12\/2017","air_temperature_celcius":19,"relative_humidity":59.7,"windspeed_knots":7.4,"max_wind_speed":14.0,"precipitation ":" 0.63G"},{"station":948702,"date":"30\/12\/2017","air_temperature_celcius":16,"relative_humidity":51.5,"windspeed_knots":8.7,"max_wind_speed":15.0,"precipitation ":" 0.02G"},{"station":948702,"date":"31\/12\/2017","air_temperature_celcius":18,"relative_humidity":53.6,"windspeed_knots":7.9,"max_wind_speed":15.9,"precipitation ":" 0.00G"},{"station":948702,"date":"1\/01\/2018","air_temperature_celcius":19,"relative_humidity":52.9,"windspeed_knots":8.1,"max_wind_speed":15.0,"precipitation ":" 0.00I"}]